aa_buybacks-0.1.6.dist-info/licenses/LICENSE
buybacks/__init__.py
buybacks/admin.py
buybacks/app_settings.py
buybacks/apps.py
buybacks/auth_hooks.py
buybacks/constants.py
buybacks/forms.py
buybacks/helpers.py
buybacks/managers.py
buybacks/models.py
buybacks/tasks.py
buybacks/urls.py
buybacks/utils.py
buybacks/validators.py
buybacks/management/commands/buybacks_load_types.py
buybacks/migrations/0001_initial.py
buybacks/migrations/0002_programs.py
buybacks/migrations/0003_contracts.py
buybacks/migrations/__init__.py
buybacks/static/buybacks/js/autocomplete.js
buybacks/static/buybacks/js/bootstrap-autocomplete.min.js
buybacks/static/buybacks/js/notify.js
buybacks/templates/buybacks/base.html
buybacks/templates/buybacks/index.html
buybacks/templates/buybacks/menu.html
buybacks/templates/buybacks/notification_edit.html
buybacks/templates/buybacks/notifications.html
buybacks/templates/buybacks/page.html
buybacks/templates/buybacks/program.html
buybacks/templates/buybacks/program_add.html
buybacks/templates/buybacks/program_add_item.html
buybacks/templates/buybacks/program_add_location.html
buybacks/templates/buybacks/program_calculate.html
buybacks/templates/buybacks/stats.html
buybacks/templatetags/__init__.py
buybacks/templatetags/date.py
buybacks/templatetags/dict.py
buybacks/templatetags/number.py
buybacks/views/__init__.py
buybacks/views/common.py
buybacks/views/notifications.py
buybacks/views/programs.py
buybacks/views/stats.py
aa_buybacks-0.1.6.dist-info/METADATA
aa_buybacks-0.1.6.dist-info/WHEEL
aa_buybacks-0.1.6.dist-info/top_level.txt
aa_buybacks-0.1.6.dist-info/RECORD
