Metadata-Version: 2.4
Name: aa-buybacks
Version: 0.1.6
Summary: Buyback program management app for Alliance Auth
Home-page: https://gitlab.com/pksunkara/aa-buybacks
Author: Pavan Kumar Sunkara
Author-email: pavan.sss1991@gmail.com
License: MIT
Classifier: Environment :: Web Environment
Classifier: Framework :: Django
Classifier: Framework :: Django :: 3.1
Classifier: Intended Audience :: Developers
Classifier: License :: OSI Approved :: MIT License
Classifier: Operating System :: OS Independent
Classifier: Programming Language :: Python
Classifier: Programming Language :: Python :: 3.6
Classifier: Topic :: Internet :: WWW/HTTP
Classifier: Topic :: Internet :: WWW/HTTP :: Dynamic Content
Requires-Python: ~=3.6
License-File: LICENSE
Requires-Dist: allianceauth>=2.8.0
Requires-Dist: celery-once>=2.0.1
Requires-Dist: django-esi>=2.0.4
Requires-Dist: django-eveuniverse>=0.6.1
Requires-Dist: django-navhelper
Requires-Dist: requests
Dynamic: author
Dynamic: author-email
Dynamic: classifier
Dynamic: description
Dynamic: description-content-type
Dynamic: home-page
Dynamic: license
Dynamic: license-file
Dynamic: requires-dist
Dynamic: requires-python
Dynamic: summary
